{
  "action": {
    "description": "Minority Committee Report: Ought to Pass with Amendment # 2026-1511h",
    "occurred_at": "2026-04-28",
    "jurisdiction_id": "~{\"classification\": \"lower\"}",
    "session_id": "2026",
    "entity_type": "bill",
    "classifications": [
      "committee-passage-favorable"
    ],
    "related_entities": [],
    "sources": [
      {
        "url": "https://gc.nh.gov/bill_Status/billinfo.aspx?id=1231&inflect=2",
        "note": ""
      }
    ]
  },
  "bill_id": "SB481"
}