{
  "legislative_session": "2026",
  "identifier": "SB530",
  "title": "relative to fetal death reporting to the Centers for Disease Control.",
  "from_organization": "~{\"classification\": \"upper\"}",
  "classification": [
    "bill"
  ],
  "subject": [],
  "abstracts": [],
  "other_titles": [],
  "other_identifiers": [
    {
      "identifier": "ocd-bill-nh-2026-sb530"
    }
  ],
  "actions": [
    {
      "description": "Introduced 01/07/2026 and Referred to Executive Departments and Administration;  SJ 1",
      "date": "2025-11-24",
      "organization_id": "~{\"classification\": \"upper\"}",
      "classification": [
        "introduction",
        "referral-committee"
      ],
      "related_entities": [],
      "_processing": {
        "log_file_created": "2026-07-14T18:52:57Z"
      }
    },
    {
      "description": "Hearing: 01/21/2026, Room 103, SH, 01:40 pm;  SC 2",
      "date": "2026-01-15",
      "organization_id": "~{\"classification\": \"upper\"}",
      "classification": [],
      "related_entities": [],
      "_processing": {
        "log_file_created": "2026-07-14T18:52:57Z"
      }
    },
    {
      "description": "Committee Report: Ought to Pass, 01/29/2026; Vote 4-0; CC;  SC 3",
      "date": "2026-01-22",
      "organization_id": "~{\"classification\": \"upper\"}",
      "classification": [
        "committee-passage-favorable"
      ],
      "related_entities": [],
      "_processing": {
        "log_file_created": "2026-07-14T18:52:57Z"
      }
    },
    {
      "description": "Ought to Pass: MA, VV; OT3rdg; 01/29/2026;  SJ 2",
      "date": "2026-01-29",
      "organization_id": "~{\"classification\": \"upper\"}",
      "classification": [
        "committee-passage-favorable",
        "passage"
      ],
      "related_entities": [],
      "_processing": {
        "log_file_created": "2026-07-14T18:52:57Z"
      }
    },
    {
      "description": "Introduced (in recess of) 02/19/2026 and referred to Executive Departments and Administration  HJ 5  P. 124",
      "date": "2026-02-26",
      "organization_id": "~{\"classification\": \"lower\"}",
      "classification": [
        "introduction",
        "referral-committee"
      ],
      "related_entities": [],
      "_processing": {
        "log_file_created": "2026-07-14T18:52:57Z"
      }
    },
    {
      "description": "==CANCELLED== Public Hearing: 03/19/2026 01:00 pm GP 231",
      "date": "2026-03-10",
      "organization_id": "~{\"classification\": \"lower\"}",
      "classification": [],
      "related_entities": [],
      "_processing": {
        "log_file_created": "2026-07-14T18:52:57Z"
      }
    },
    {
      "description": "==CANCELLED== Public Hearing: 03/25/2026 01:55 pm GP 231",
      "date": "2026-03-18",
      "organization_id": "~{\"classification\": \"lower\"}",
      "classification": [],
      "related_entities": [],
      "_processing": {
        "log_file_created": "2026-07-14T18:52:57Z"
      }
    },
    {
      "description": "Public Hearing: 03/25/2026 01:40 pm GP 231",
      "date": "2026-03-19",
      "organization_id": "~{\"classification\": \"lower\"}",
      "classification": [],
      "related_entities": [],
      "_processing": {
        "log_file_created": "2026-07-14T18:52:57Z"
      }
    },
    {
      "description": "Executive Session: 03/25/2026 01:40 pm GP 231",
      "date": "2026-03-25",
      "organization_id": "~{\"classification\": \"lower\"}",
      "classification": [],
      "related_entities": [],
      "_processing": {
        "log_file_created": "2026-07-14T18:52:57Z"
      }
    },
    {
      "description": "Committee Report: Ought to Pass  03/25/2026 (Vote 16-0; CC)",
      "date": "2026-04-08",
      "organization_id": "~{\"classification\": \"lower\"}",
      "classification": [
        "committee-passage-favorable"
      ],
      "related_entities": [],
      "_processing": {
        "log_file_created": "2026-07-14T18:52:57Z"
      }
    },
    {
      "description": "Ought to Pass: MA VV 04/23/2026  HJ 11",
      "date": "2026-04-23",
      "organization_id": "~{\"classification\": \"lower\"}",
      "classification": [
        "committee-passage-favorable",
        "passage"
      ],
      "related_entities": [],
      "_processing": {
        "log_file_created": "2026-07-14T18:52:57Z"
      }
    },
    {
      "description": "Enrolled Adopted, VV, (In recess 06/04/2026);  SJ 14",
      "date": "2026-06-17",
      "organization_id": "~{\"classification\": \"upper\"}",
      "classification": [
        "enrolled"
      ],
      "related_entities": [],
      "_processing": {
        "log_file_created": "2026-07-14T18:52:57Z"
      }
    },
    {
      "description": "Enrolled (in recess of) 06/04/2026  HJ 15",
      "date": "2026-06-17",
      "organization_id": "~{\"classification\": \"lower\"}",
      "classification": [],
      "related_entities": [],
      "_processing": {
        "log_file_created": "2026-07-14T18:52:57Z"
      }
    }
  ],
  "sponsorships": [
    {
      "name": "Cindy Rosenwald",
      "classification": "primary",
      "entity_type": "person",
      "primary": true,
      "person_id": "~{\"name\": \"Cindy Rosenwald\"}",
      "organization_id": null
    },
    {
      "name": "Keith Erf",
      "classification": "cosponsor",
      "entity_type": "person",
      "primary": false,
      "person_id": "~{\"name\": \"Keith Erf\"}",
      "organization_id": null
    },
    {
      "name": "Bob J. Lynn",
      "classification": "cosponsor",
      "entity_type": "person",
      "primary": false,
      "person_id": "~{\"name\": \"Bob J. Lynn\"}",
      "organization_id": null
    },
    {
      "name": "Howard Pearl",
      "classification": "cosponsor",
      "entity_type": "person",
      "primary": false,
      "person_id": "~{\"name\": \"Howard Pearl\"}",
      "organization_id": null
    },
    {
      "name": "Carrie Sorensen",
      "classification": "cosponsor",
      "entity_type": "person",
      "primary": false,
      "person_id": "~{\"name\": \"Carrie Sorensen\"}",
      "organization_id": null
    }
  ],
  "related_bills": [],
  "versions": [
    {
      "note": "Introduced",
      "links": [
        {
          "url": "https://gc.nh.gov/bill_Status/pdf.aspx?id=22177&q=billVersion",
          "media_type": "application/pdf"
        }
      ],
      "date": "",
      "classification": ""
    },
    {
      "note": "Version adopted by both bodies",
      "links": [
        {
          "url": "https://gc.nh.gov/bill_Status/pdf.aspx?id=31443&q=billVersion",
          "media_type": "application/pdf"
        }
      ],
      "date": "",
      "classification": ""
    }
  ],
  "documents": [],
  "citations": [],
  "sources": [
    {
      "url": "https://gc.nh.gov/bill_Status/billinfo.aspx?id=1328&inflect=2",
      "note": ""
    }
  ],
  "extras": {
    "LSR": "2137",
    "_code": "4070"
  },
  "jurisdiction": {
    "id": "ocd-jurisdiction/country:us/state:nh/government",
    "name": "New Hampshire",
    "classification": "state",
    "division_id": "ocd-division/country:us/state:nh"
  },
  "_processing": {
    "logs_latest_update": "2026-07-14T18:52:57Z"
  }
}